platerec/__init__.py
platerec/cli.py
platerec/inference_image.py
platerec/inference_video.py
platerec/platerec.py
platerec/tokenizer.py
platerec/artifacts/decoder.onnx
platerec/artifacts/encoder.onnx
platerec/artifacts/tokenizer.json
platerec-0.0.3.dist-info/METADATA
platerec-0.0.3.dist-info/WHEEL
platerec-0.0.3.dist-info/entry_points.txt
platerec-0.0.3.dist-info/top_level.txt
platerec-0.0.3.dist-info/RECORD
