Metadata-Version: 2.2
Name: platerec
Version: 0.0.3
Summary: Read license plates
Home-page: https://github.com/pstwh/platerec
Keywords: plate,ocr,read,alpr
Requires-Python: >=3.5, <4
Requires-Dist: pillow==10.4.0
Requires-Dist: opencv-python-headless==4.10.0.84
Requires-Dist: platedet==0.0.2
Provides-Extra: cpu
Requires-Dist: onnxruntime==1.20.1; extra == "cpu"
Provides-Extra: gpu
Requires-Dist: onnxruntime-gpu==1.20.1; extra == "gpu"
Dynamic: description
Dynamic: description-content-type
Dynamic: home-page
Dynamic: keywords
Dynamic: provides-extra
Dynamic: requires-dist
Dynamic: requires-python
Dynamic: summary
